LICENSE
MANIFEST.in
README.md
setup.py
libbgg/__init__.py
libbgg/apibase.py
libbgg/apiv1.py
libbgg/apiv2.py
libbgg/errors.py
libbgg/infodict.py
py_bgg.egg-info/PKG-INFO
py_bgg.egg-info/SOURCES.txt
py_bgg.egg-info/dependency_links.txt
py_bgg.egg-info/top_level.txt